irpf90-2.0.5.data/scripts/irpf90
irpf90-2.0.5.data/scripts/irpf90_indent
irpf90-2.0.5.data/scripts/irpman
irpf90_libs/__init__.py
irpf90_libs/checkpoint.py
irpf90_libs/codelet.py
irpf90_libs/command_line.py
irpf90_libs/create_man.py
irpf90_libs/emacs.py
irpf90_libs/error.py
irpf90_libs/init.py
irpf90_libs/irp_stack.py
irpf90_libs/irpf90.py
irpf90_libs/irpf90_indent.py
irpf90_libs/irpf90_t.py
irpf90_libs/irpman.py
irpf90_libs/locks.py
irpf90_libs/makefile.py
irpf90_libs/module.py
irpf90_libs/modules.py
irpf90_libs/ninja.py
irpf90_libs/parsed_text.py
irpf90_libs/preprocessed_text.py
irpf90_libs/profile.py
irpf90_libs/regexps.py
irpf90_libs/subroutine.py
irpf90_libs/subroutines.py
irpf90_libs/touches.py
irpf90_libs/util.py
irpf90_libs/variable.py
irpf90_libs/variables.py
irpf90_libs/version.py
irpf90_libs/vim.py
irpf90-2.0.5.dist-info/LICENSE.txt
irpf90-2.0.5.dist-info/METADATA
irpf90-2.0.5.dist-info/WHEEL
irpf90-2.0.5.dist-info/top_level.txt
irpf90-2.0.5.dist-info/RECORD
