Metadata-Version: 2.1
Name: irpf90
Version: 2.0.5
Summary: IRPF90 is a Fortran90 preprocessor written in Python for programming using the Implicit Reference to Parameters (IRP) method. It simplifies the development of large fortran codes in the field of scientific high performance computing.
Home-page: https://irpf90.ups-tlse.fr
Author: Anthony Scemama
Author-email: scemama@irsamc.ups-tlse.fr
License: UNKNOWN
Download-URL: https://gitlab.com/scemama/irpf90/-/archive/v2.0.5/irpf90-v2.0.5.tar.gz
Keywords: programming,fortran,IRP
Platform: UNKNOWN
Classifier: Programming Language :: Python :: 3
Classifier: Programming Language :: Fortran
Classifier: License :: OSI Approved :: GNU General Public License v2 or later (GPLv2+)
Classifier: Operating System :: POSIX :: Linux
